<?xml version="1.0" encoding="UTF-8"?>
<metadata xml:lang="en"><Esri><CreaDate>20191029</CreaDate><CreaTime>12184400</CreaTime><ArcGISFormat>1.0</ArcGISFormat><SyncOnce>TRUE</SyncOnce><DataProperties><lineage><Process ToolSource="c:\program files (x86)\arcgis\desktop10.6\ArcToolbox\Toolboxes\Data Management Tools.tbx\CalculateField" Date="20181108" Time="151857">CalculateField CD_FoodInsecurity1 PctFoodI_1 "-" VB #</Process><Process ToolSource="c:\program files (x86)\arcgis\desktop10.6\ArcToolbox\Toolboxes\Data Management Tools.tbx\CalculateField" Date="20181108" Time="151907">CalculateField CD_FoodInsecurity1 PctFoodInC "-1" VB #</Process><Process ToolSource="c:\program files (x86)\arcgis\desktop10.6\ArcToolbox\Toolboxes\Data Management Tools.tbx\CalculateField" Date="20181108" Time="151954">CalculateField CD_FoodInsecurity1 PctFoodI_1 [PctFoodIns]+".0" VB #</Process><Process ToolSource="c:\program files (x86)\arcgis\desktop10.6\ArcToolbox\Toolboxes\Data Management Tools.tbx\CalculateField" Date="20181108" Time="152141">CalculateField CD_FoodInsecurity1 PctFoodInC "1" VB #</Process><Process ToolSource="c:\program files (x86)\arcgis\desktop10.6\ArcToolbox\Toolboxes\Data Management Tools.tbx\CalculateField" Date="20181108" Time="152230">CalculateField CD_FoodInsecurity1 PctFoodInC "2" VB #</Process><Process ToolSource="c:\program files (x86)\arcgis\desktop10.6\ArcToolbox\Toolboxes\Data Management Tools.tbx\CalculateField" Date="20181108" Time="152245">CalculateField CD_FoodInsecurity1 PctFoodInC "3" VB #</Process><Process ToolSource="c:\program files (x86)\arcgis\desktop10.6\ArcToolbox\Toolboxes\Data Management Tools.tbx\CalculateField" Date="20181108" Time="152258">CalculateField CD_FoodInsecurity1 PctFoodInC "4" VB #</Process><Process ToolSource="c:\program files (x86)\arcgis\desktop10.6\ArcToolbox\Toolboxes\Data Management Tools.tbx\CalculateField" Date="20181108" Time="152318">CalculateField CD_FoodInsecurity1 PctFoodInC "5" VB #</Process></lineage></DataProperties></Esri></metadata>
